rezkaAPI/__init__.py
rezkaAPI/parser.py
rezkaAPI-0.1.0.dist-info/LICENSE
rezkaAPI-0.1.0.dist-info/METADATA
rezkaAPI-0.1.0.dist-info/WHEEL
rezkaAPI-0.1.0.dist-info/top_level.txt
rezkaAPI-0.1.0.dist-info/RECORD
