Metadata-Version: 2.1
Name: rezkaAPI
Version: 0.1.0
Summary: Helps to get a variety of information from hdrezka.ag
Author-email: Maksim Burlakov <maks.burlakof@gmail.com>
License: MIT License        
Project-URL: Homepage, https://github.com/maks-burlakof/hdrezkaAPI
Project-URL: Bug Tracker, https://github.com/maks-burlakof/hdrezkaAPI/issues
Keywords: hdrezka,kinopub,API
Classifier: Programming Language :: Python :: 3
Classifier: License :: OSI Approved :: MIT License
Classifier: Operating System :: OS Independent
Requires-Python: >=3.7
License-File: LICENSE
Requires-Dist: selenium (>=4.5.0)
